bikram_sambat/__init__.py
bikram_sambat/bs_date.py
bikram_sambat/bs_datetime.py
bikram_sambat/bs_time.py
bikram_sambat/bs_timedelta.py
bikram_sambat/bs_timezone.py
bikram_sambat/config.py
bikram_sambat/constants.py
bikram_sambat/conversion.py
bikram_sambat/exceptions.py
bikram_sambat/strptime.py
bikram_sambat/data/calendar_data.py
bikram_sambat/data/__pycache__/calendar_data.cpython-310.pyc
bikram_sambat/data/__pycache__/calendar_data.cpython-312.pyc
bikram_sambat/data/__pycache__/calender_data.cpython-312.pyc
bikram_sambat-0.1.0.dist-info/licenses/LICENSE
bikram_sambat-0.1.0.dist-info/METADATA
bikram_sambat-0.1.0.dist-info/WHEEL
bikram_sambat-0.1.0.dist-info/top_level.txt
bikram_sambat-0.1.0.dist-info/RECORD
