Metadata-Version: 2.4
Name: bikram-sambat
Version: 0.1.0
Summary: A comprehensive, modern, and easy-to-use Python library for the Bikram Sambat (BS) calendar system.
Author-email: Ashok Dhakal <info@ashokdhakal.com>
License: Copyright (c) 2025 Bikram Sambat Contributors
Project-URL: Homepage, https://github.com/ashok095/bikram-sambat
Project-URL: Repository, https://github.com/ashok095/bikram-sambat
Project-URL: Bug Tracker, https://github.com/ashok095/bikram-sambat/issues
Project-URL: Documentation, https://bikram-sambat.readthedocs.io
Classifier: Programming Language :: Python :: 3
Classifier: Programming Language :: Python :: 3.8
Classifier: Programming Language :: Python :: 3.9
Classifier: Programming Language :: Python :: 3.10
Classifier: Programming Language :: Python :: 3.11
Classifier: Programming Language :: Python :: 3.12
Classifier: License :: OSI Approved :: MIT License
Classifier: Operating System :: OS Independent
Classifier: Intended Audience :: Developers
Classifier: Topic :: Software Development :: Libraries :: Python Modules
Classifier: Topic :: Office/Business :: Scheduling
Classifier: Natural Language :: English
Classifier: Natural Language :: Nepali
Requires-Python: >=3.8
License-File: LICENSE
Requires-Dist: pytz
Provides-Extra: test
Requires-Dist: pytest; extra == "test"
Requires-Dist: pytest-cov; extra == "test"
Dynamic: license-file
